optika/__init__.py
optika/_caching.py
optika/_util.py
optika/_util_test.py
optika/mixins.py
optika/propagators.py
optika/surfaces.py
optika/systems.py
optika/_tests/__init__.py
optika/_tests/test_mixins.py
optika/_tests/test_propagators.py
optika/_tests/test_surfaces.py
optika/_tests/test_systems.py
optika/apertures/__init__.py
optika/apertures/_apertures.py
optika/apertures/_apertures_test.py
optika/chemicals/__init__.py
optika/chemicals/_chemicals.py
optika/chemicals/_tests/__init__.py
optika/chemicals/_tests/test_chemicals.py
optika/chemicals/nk/AAACATALOG.TXT
optika/chemicals/nk/Ac.nk
optika/chemicals/nk/Ac_llnl_cxro.nk
optika/chemicals/nk/Ag.nk
optika/chemicals/nk/Ag2O.nk
optika/chemicals/nk/Ag2O_llnl_cxro.nk
optika/chemicals/nk/Ag_hagemann.nk
optika/chemicals/nk/Ag_leveque.nk
optika/chemicals/nk/Ag_llnl_cxro.nk
optika/chemicals/nk/Ag_palik.nk
optika/chemicals/nk/Ag_windt.nk
optika/chemicals/nk/Al.3Ga.7As.nk
optika/chemicals/nk/Al.3Ga.7As_palik.nk
optika/chemicals/nk/Al.98Si.02.nk
optika/chemicals/nk/Al.98Si.02_llnl_cxro.nk
optika/chemicals/nk/Al.99Si.01.nk
optika/chemicals/nk/Al.99Si.01_llnl_cxro.nk
optika/chemicals/nk/Al.nk
optika/chemicals/nk/Al2O3-e.nk
optika/chemicals/nk/Al2O3-e_palik.nk
optika/chemicals/nk/Al2O3.nk
optika/chemicals/nk/Al2O3_palik.nk
optika/chemicals/nk/AlAs.nk
optika/chemicals/nk/AlAs_palik.nk
optika/chemicals/nk/AlN.nk
optika/chemicals/nk/AlN_llnl_cxro.nk
optika/chemicals/nk/AlSb.nk
optika/chemicals/nk/AlSb_palik.nk
optika/chemicals/nk/Al_llnl_cxro.nk
optika/chemicals/nk/Al_palik.nk
optika/chemicals/nk/Al_shiles.nk
optika/chemicals/nk/Al_windt.nk
optika/chemicals/nk/Au.nk
optika/chemicals/nk/Au_canfield.nk
optika/chemicals/nk/Au_chen.nk
optika/chemicals/nk/Au_hagemann.nk
optika/chemicals/nk/Au_llnl_cxro.nk
optika/chemicals/nk/Au_nilsson.nk
optika/chemicals/nk/Au_palik.nk
optika/chemicals/nk/Au_weaver.nk
optika/chemicals/nk/Au_windt.nk
optika/chemicals/nk/B.nk
optika/chemicals/nk/B2O3.nk
optika/chemicals/nk/B2O3_llnl_cxro.nk
optika-1.0.1.dist-info/METADATA
optika-1.0.1.dist-info/WHEEL
optika-1.0.1.dist-info/top_level.txt
optika-1.0.1.dist-info/RECORD
