Metadata-Version: 2.4
Name: optika
Version: 1.0.1
Summary: A Python library for simulating optical systems, similar to Zemax
Author-email: "Roy T. Smart" <roytsmart@gmail.com>
Project-URL: Homepage, https://github.com/sun-data/optika
Project-URL: Documentation, https://optika.readthedocs.io/en/latest
Classifier: Programming Language :: Python :: 3
Requires-Python: >=3.11
Requires-Dist: astropy!=6.1.5
Requires-Dist: named-arrays~=1.0
Requires-Dist: pymupdf
Requires-Dist: joblib
Provides-Extra: test
Requires-Dist: pytest; extra == "test"
Provides-Extra: doc
Requires-Dist: pytest; extra == "doc"
Requires-Dist: matplotlib; extra == "doc"
Requires-Dist: graphviz; extra == "doc"
Requires-Dist: sphinx-autodoc-typehints; extra == "doc"
Requires-Dist: sphinxcontrib-bibtex; extra == "doc"
Requires-Dist: pydata-sphinx-theme; extra == "doc"
Requires-Dist: ipykernel; extra == "doc"
Requires-Dist: jupyter-sphinx; extra == "doc"
Requires-Dist: nbsphinx; extra == "doc"
Requires-Dist: sphinx-codeautolink; extra == "doc"
Requires-Dist: sphinx-favicon; extra == "doc"
